{
  "openapi": "3.0.4",
  "info": {
    "title": "BreathingFree API",
    "version": "v1"
  },
  "paths": {
    "/api/Auth/register": {
      "post": {
        "tags": [
          "Auth"
        ],
        "requestBody": {
          "content": {
            "application/json": {
              "schema": {
                "$ref": "#/components/schemas/RegisterModel"
              }
            },
            "text/json": {
              "schema": {
                "$ref": "#/components/schemas/RegisterModel"
              }
            },
            "application/*+json": {
              "schema": {
                "$ref": "#/components/schemas/RegisterModel"
              }
            }
          }
        },
        "responses": {
          "200": {
            "description": "OK"
          }
        }
      }
    },
    "/api/Auth/login": {
      "post": {
        "tags": [
          "Auth"
        ],
        "requestBody": {
          "content": {
            "application/json": {
              "schema": {
                "$ref": "#/components/schemas/LoginModel"
              }
            },
            "text/json": {
              "schema": {
                "$ref": "#/components/schemas/LoginModel"
              }
            },
            "application/*+json": {
              "schema": {
                "$ref": "#/components/schemas/LoginModel"
              }
            }
          }
        },
        "responses": {
          "200": {
            "description": "OK"
          }
        }
      }
    },
    "/api/Message/send": {
      "post": {
        "tags": [
          "Message"
        ],
        "requestBody": {
          "content": {
            "application/json": {
              "schema": {
                "$ref": "#/components/schemas/SendMessageModel"
              }
            },
            "text/json": {
              "schema": {
                "$ref": "#/components/schemas/SendMessageModel"
              }
            },
            "application/*+json": {
              "schema": {
                "$ref": "#/components/schemas/SendMessageModel"
              }
            }
          }
        },
        "responses": {
          "200": {
            "description": "OK"
          }
        }
      }
    },
    "/api/Message/conversations": {
      "get": {
        "tags": [
          "Message"
        ],
        "responses": {
          "200": {
            "description": "OK"
          }
        }
      }
    },
    "/api/Message/messages/{otherUserId}": {
      "get": {
        "tags": [
          "Message"
        ],
        "parameters": [
          {
            "name": "otherUserId",
            "in": "path",
            "required": true,
            "schema": {
              "type": "integer",
              "format": "int32"
            }
          }
        ],
        "responses": {
          "200": {
            "description": "OK"
          }
        }
      }
    },
    "/api/Ranking": {
      "get": {
        "tags": [
          "Ranking"
        ],
        "responses": {
          "200": {
            "description": "OK"
          }
        }
      }
    },
    "/api/Ranking/my-ranking": {
      "get": {
        "tags": [
          "Ranking"
        ],
        "responses": {
          "200": {
            "description": "OK"
          }
        }
      }
    }
  },
  "components": {
    "schemas": {
      "LoginModel": {
        "type": "object",
        "properties": {
          "email": {
            "type": "string",
            "nullable": true
          },
          "password": {
            "type": "string",
            "nullable": true
          }
        },
        "additionalProperties": false
      },
      "RegisterModel": {
        "type": "object",
        "properties": {
          "fullName": {
            "type": "string",
            "nullable": true
          },
          "email": {
            "type": "string",
            "nullable": true
          },
          "password": {
            "type": "string",
            "nullable": true
          },
          "gender": {
            "type": "string",
            "nullable": true
          },
          "dob": {
            "type": "string",
            "nullable": true
          }
        },
        "additionalProperties": false
      },
      "SendMessageModel": {
        "type": "object",
        "properties": {
          "receiverId": {
            "type": "integer",
            "format": "int32"
          },
          "content": {
            "type": "string",
            "nullable": true
          }
        },
        "additionalProperties": false
      }
    }
  }
}